taxoniq_accessions/__init__.py
taxoniq_accessions/db.marisa
taxoniq_accessions-2021.3.23.dist-info/METADATA
taxoniq_accessions-2021.3.23.dist-info/WHEEL
taxoniq_accessions-2021.3.23.dist-info/top_level.txt
taxoniq_accessions-2021.3.23.dist-info/RECORD
