Metadata-Version: 2.1
Name: taxoniq-accessions
Version: 2021.3.23
Summary: Taxoniq accession index for NCBI BLAST databases
Home-page: https://github.com/chanzuckerberg/taxoniq
Author: Andrey Kislyuk
Author-email: akislyuk@chanzuckerberg.com
License: MIT License
Platform: UNKNOWN
